{
  "name": "trends-in-siyuan",
  "author": "frostime",
  "url": "https://github.com/frostime/sy-theme-trends",
  "version": "0.4.2",
  "minAppVersion": "3.1.20",
  "displayName": {
    "default": "Trends in SiYuan",
    "zh_CN": "Trends in SiYuan"
  },
  "description": {
    "default": "Theme for SiYuan inspired by Trends series journals.",
    "zh_CN": "仿 Trends 系列期刊主题"
  },
  "readme": {
    "default": "README.md",
    "zh_CN": "README_zh_CN.md"
  },
  "funding": {
    "openCollective": "",
    "patreon": "",
    "github": "",
    "custom": [
      "https://afdian.com/a/frostime"
    ]
  },
  "modes": [
    "light"
  ]
}
